pybgcode/__init__.py
pybgcode/_bgcode.cpython-39-x86_64-linux-gnu.so
pybgcode_jneilliii-0.2.1.dist-info/METADATA
pybgcode_jneilliii-0.2.1.dist-info/WHEEL
pybgcode_jneilliii-0.2.1.dist-info/entry_points.txt
pybgcode_jneilliii-0.2.1.dist-info/RECORD
pybgcode_jneilliii-0.2.1.dist-info/licenses/LICENSE
