Metadata-Version: 2.4
Name: pybgcode-jneilliii
Version: 0.2.1
Summary: Prusa Block & Binary G-code reader / writer / converter
Author: Enrico Turri, Tomas Meszaros
License-Expression: AGPL-3.0-or-later
License-File: LICENSE
Classifier: Programming Language :: Python :: 3
Classifier: Operating System :: OS Independent
Project-URL: Homepage, https://github.com/prusa3d/libbgcode
Project-URL: Bug Tracker, https://github.com/prusa3d/libbgcode/issues
Requires-Python: >=3.7
